test_utils/__init__.py
test_utils/api/__init__.py
test_utils/api/api.py
sfdc_dummy-1.0.10.dist-info/METADATA
sfdc_dummy-1.0.10.dist-info/WHEEL
sfdc_dummy-1.0.10.dist-info/top_level.txt
sfdc_dummy-1.0.10.dist-info/RECORD
